src/__init__.py
src/__main__.py
src/bcast.py
src/recv.py
src/send.py
pysendcast-0.1.6.dist-info/METADATA
pysendcast-0.1.6.dist-info/WHEEL
pysendcast-0.1.6.dist-info/entry_points.txt
pysendcast-0.1.6.dist-info/licenses/LICENSE.txt
pysendcast-0.1.6.dist-info/RECORD
