Metadata-Version: 2.1
Name: pySendCast
Version: 0.1.6
Summary: A pure Python cross-platform program to send and receive data over local area network(LAN) with on-the-fly gzip streaming and broadcasting
Project-URL: Homepage, https://github.com/chidea/pySendCast
Author-email: "Ch.Idea" <sbw228@gmail.com>
License-File: LICENSE.txt
Classifier: License :: OSI Approved :: MIT License
Classifier: Natural Language :: English
Classifier: Operating System :: OS Independent
Classifier: Programming Language :: Python :: 3
Classifier: Topic :: Communications :: File Sharing
Classifier: Topic :: System :: Networking
